{"problems":[{"color":null,"id":0,"name":"A","title":"\uc5ec\uc6b0 \uc0ac\uc778"},{"color":null,"id":1,"name":"B","title":"\uace0\uc7a5\ub09c \uc2dc\uacc4"},{"color":null,"id":2,"name":"C","title":"\ud0c0\uc77c \ub4a4\uc9d1\uae30 (Easy)"},{"color":null,"id":3,"name":"D","title":"\uad00\uc545\uc0b0 \ub4f1\uc0b0"},{"color":null,"id":4,"name":"E","title":"\ub134\ubaa8\ub134\ubaa8 (Easy)"},{"color":null,"id":5,"name":"F","title":"\uc575\ubb34\uc0c8"},{"color":null,"id":6,"name":"G","title":"\uc154\ud2c0\ubc84\uc2a4"},{"color":null,"id":7,"name":"H","title":"\ud64d\uc0bc \uac8c\uc784 (Easy)"},{"color":null,"id":8,"name":"I","title":"\uc804\uc0dd\ud588\ub354\ub2c8 \uc2ac\ub77c\uc784 \uc5f0\uad6c\uc790\uc600\ub358 \uac74\uc5d0 \ub300\ud558\uc5ec (Easy)"}],"systemName":"DOMJudge","systemVersion":"","teams":[{"id":6,"name":"\uae40\u2606\ud658"},{"id":8,"name":"\uc774\u2606\ud558"},{"id":10,"name":"\uc774\u2606\ud559"},{"id":16,"name":"\ud64d\u2606\uc815"},{"id":17,"name":"\uc774\u2606\ud5cc"},{"id":20,"name":"\uc774\u2606\ubbfc"},{"id":21,"name":"\ucd5c\u2606\uc900"},{"id":22,"name":"\ucd5c\u2606\ud638"},{"id":25,"name":"\uc548\u2606\ucc2c"},{"id":28,"name":"\uc815\u2606\uc6b1"},{"id":30,"name":"\ucd5c\u2606\uc7ac"},{"id":32,"name":"\ub178\u2606\ubbf8"},{"id":33,"name":"\uc1a1\u2606\uc6b0"},{"id":37,"name":"\ucc28\u2606\ud0c1"},{"id":38,"name":"\uae40\u2606\uc601"},{"id":40,"name":"\ubc30\u2606\uc900"},{"id":43,"name":"\uc774\u2606\ud6c4"},{"id":44,"name":"\uc724\u2606\ud604"},{"id":45,"name":"\uc724\u2606\ud604"},{"id":47,"name":"\uae40\u2606\ud604_\uc218\ub9ac"},{"id":49,"name":"\uc774\u2606\uaddc"},{"id":50,"name":"\ubc15\u2606\uc6d0"},{"id":51,"name":"\ubc31\u2606\uc6d0"},{"id":53,"name":"\uc774\u2606\ucc2c"},{"id":55,"name":"\ucd5c\u2606\ud6c8"},{"id":57,"name":"\ubc15\u2606\ucc2c"},{"id":58,"name":"\uc870\u2606\ud604"},{"id":59,"name":"\uc591\u2606\uc601"},{"id":60,"name":"\uae40\u2606\ubbfc"},{"id":61,"name":"\uc774\u2606\uc6b4"},{"id":63,"name":"Tester"}],"title":"SNUPC 2017 Division 2"}